matterapi/__init__.py
matterapi/client/async_client.py
matterapi/client/base.py
matterapi/client/exceptions.py
matterapi/client/sync_client.py
matterapi/endpoints/async_api/__init__.py
matterapi/endpoints/async_api/authentication.py
matterapi/endpoints/async_api/bleve.py
matterapi/endpoints/async_api/bots.py
matterapi/endpoints/async_api/brand.py
matterapi/endpoints/async_api/channels.py
matterapi/endpoints/async_api/cloud.py
matterapi/endpoints/async_api/cluster.py
matterapi/endpoints/async_api/commands.py
matterapi/endpoints/async_api/compliance.py
matterapi/endpoints/async_api/data_retention.py
matterapi/endpoints/async_api/elasticsearch.py
matterapi/endpoints/async_api/emoji.py
matterapi/endpoints/async_api/exports.py
matterapi/endpoints/async_api/files.py
matterapi/endpoints/async_api/groups.py
matterapi/endpoints/async_api/imports.py
matterapi/endpoints/async_api/integration_actions.py
matterapi/endpoints/async_api/jobs.py
matterapi/endpoints/async_api/ldap.py
matterapi/endpoints/async_api/migrate.py
matterapi/endpoints/async_api/oauth.py
matterapi/endpoints/async_api/open_graph.py
matterapi/endpoints/async_api/permissions.py
matterapi/endpoints/async_api/plugins.py
matterapi/endpoints/async_api/posts.py
matterapi/endpoints/async_api/preferences.py
matterapi/endpoints/async_api/reactions.py
matterapi/endpoints/async_api/roles.py
matterapi/endpoints/async_api/root.py
matterapi/endpoints/async_api/saml.py
matterapi/endpoints/async_api/schemes.py
matterapi/endpoints/async_api/search.py
matterapi/endpoints/async_api/shared_channels.py
matterapi/endpoints/async_api/status.py
matterapi/endpoints/async_api/system.py
matterapi/endpoints/async_api/teams.py
matterapi/endpoints/async_api/terms_of_service.py
matterapi/endpoints/async_api/threads.py
matterapi/endpoints/async_api/uploads.py
matterapi/endpoints/async_api/users.py
matterapi/endpoints/async_api/webhooks.py
matterapi/endpoints/base.py
matterapi/endpoints/sync_api/__init__.py
matterapi-0.4.1.dist-info/LICENSE
matterapi-0.4.1.dist-info/WHEEL
matterapi-0.4.1.dist-info/METADATA
matterapi-0.4.1.dist-info/RECORD
