Metadata-Version: 2.1
Name: matterapi
Version: 0.4.1
Summary: A client library for Mattermost API supporting sync/async
Home-page: https://matterapi.readthedocs.io/
License: MIT
Author: Georg Merzdovnik
Requires-Python: >=3.7,<4.0.0
Classifier: License :: OSI Approved :: MIT License
Classifier: Programming Language :: Python :: 3
Classifier: Programming Language :: Python :: 3.10
Classifier: Programming Language :: Python :: 3.7
Classifier: Programming Language :: Python :: 3.8
Classifier: Programming Language :: Python :: 3.9
Requires-Dist: httpx (>=0.21.0)
Requires-Dist: pydantic (>=1.9.0,<2.0.0)
Requires-Dist: python-dateutil (>=2.8.0,<3.0.0)
Requires-Dist: websockets (>=10.0,<11.0)
Project-URL: Repository, https://github.com/gmerz/MatterApi
